lampa/__init__.py
lampa/input.py
lampa/main.py
lampa/project.py
lampa-0.1.4.dist-info/LICENSE
lampa-0.1.4.dist-info/WHEEL
lampa-0.1.4.dist-info/METADATA
lampa-0.1.4.dist-info/RECORD
